target_datadotworld/__init__.py
target_datadotworld/api_client.py
target_datadotworld/cli.py
target_datadotworld/exceptions.py
target_datadotworld/singer_analytics.py
target_datadotworld/target.py
target_datadotworld/utils.py
target_datadotworld-1.0.1.dist-info/METADATA
target_datadotworld-1.0.1.dist-info/RECORD
target_datadotworld-1.0.1.dist-info/WHEEL
target_datadotworld-1.0.1.dist-info/entry_points.txt
target_datadotworld-1.0.1.dist-info/top_level.txt
