Metadata-Version: 2.1
Name: target-datadotworld
Version: 1.0.1
Summary: Singer target for data.world
Home-page: http://github.com/datadotworld/target-datadotworld
Author: data.world
Author-email: help@data.world
License: Apache 2.0
Keywords: data.world dataset singer target
Platform: UNKNOWN
Classifier: Development Status :: 4 - Beta
Classifier: Intended Audience :: Developers
Classifier: Intended Audience :: Information Technology
Classifier: Intended Audience :: System Administrators
Classifier: License :: OSI Approved :: Apache Software License
Classifier: Operating System :: OS Independent
Classifier: Programming Language :: Python :: 3 :: Only
Classifier: Programming Language :: Python :: 3
Classifier: Programming Language :: Python :: 3.6
Classifier: Topic :: Database :: Database Engines/Servers
Classifier: Topic :: Scientific/Engineering :: Information Analysis
Requires-Dist: backoff (<2.0a,>=1.3.0)
Requires-Dist: click (<7.0a,>=6.7)
Requires-Dist: jsonschema (<3.0a,>=2.6.0)
Requires-Dist: pyjwt (<2.0a,>=1.5.3)
Requires-Dist: requests (<3.0a,>=2.4.0)
Requires-Dist: singer-python (<6.0a,>=5.0.4)
